ocr_weighted_levenhstein/__init__.py
ocr_weighted_levenhstein/data/delete.npy
ocr_weighted_levenhstein/data/insert.npy
ocr_weighted_levenhstein/data/subs.npy
ocr_weighted_levenhstein-1.0.0.dist-info/LICENSE
ocr_weighted_levenhstein-1.0.0.dist-info/METADATA
ocr_weighted_levenhstein-1.0.0.dist-info/WHEEL
ocr_weighted_levenhstein-1.0.0.dist-info/top_level.txt
ocr_weighted_levenhstein-1.0.0.dist-info/RECORD
