Metadata-Version: 2.1
Name: ocr-weighted-levenhstein
Version: 1.0.0
Summary: Weights for levenshtein distance based on ocr character similarity
Author-email: Joan Capell <author@example.com>
License: Copyright (c) 2018 The Python Packaging Authority        
Project-URL: Homepage, https://github.com/zas97/ocr_weighted_levenshtein
Project-URL: Bug Tracker, https://github.com/zas97/ocr_weighted_levenshtein/issues
Classifier: Programming Language :: Python :: 3
Classifier: License :: OSI Approved :: MIT License
Classifier: Operating System :: OS Independent
Requires-Python: >=3.6
License-File: LICENSE
